rule34scraper/__init__.py
rule34scraper/client.py
rule34scraper/models.py
rule34scraper/parser.py
rule34scraper-1.0.1.dist-info/METADATA
rule34scraper-1.0.1.dist-info/WHEEL
rule34scraper-1.0.1.dist-info/licenses/LICENSE
rule34scraper-1.0.1.dist-info/RECORD
