Metadata-Version: 2.4
Name: rule34scraper
Version: 1.0.1
Summary: A fast Python API wrapper for rule34 image board
Project-URL: Homepage, https://github.com/whatimdoingwithmylife-sudo/rule34wrapper
Project-URL: Repository, https://github.com/whatimdoingwithmylife-sudo/rule34wrapper
Author: whatimdoingwithmylife-sudo
License-Expression: MIT
License-File: LICENSE
Keywords: api,imageboard,scraper,wrapper
Classifier: Development Status :: 3 - Alpha
Classifier: Intended Audience :: Developers
Classifier: License :: OSI Approved :: MIT License
Classifier: Programming Language :: Python :: 3
Classifier: Programming Language :: Python :: 3.9
Classifier: Programming Language :: Python :: 3.10
Classifier: Programming Language :: Python :: 3.11
Classifier: Programming Language :: Python :: 3.12
Requires-Python: >=3.9
Requires-Dist: httpx>=0.24.0
Requires-Dist: selectolax>=0.3.0
Provides-Extra: dev
Requires-Dist: pytest-asyncio>=0.21; extra == 'dev'
Requires-Dist: pytest>=7.0; extra == 'dev'
